[
  {
    "metadata": "dashboard",
    "development": "http://localhost:3000/api/dashboard",
    "production": "http://34.70.243.4/personal/public/api/dashboard"
  },
  {
    "metadata": "option",
    "development": "http://localhost:3000/api/option",
    "production": "http://34.70.243.4/personal/public/api/option"
  },
  {
    "metadata": "task",
    "development": "http://localhost:3000/api/task",
    "production": "http://34.70.243.4/personal/public/api/task"
  },
  {
    "metadata": "taskList",
    "development": "http://localhost:3000/api/taskList",
    "production": "http://34.70.243.4/personal/public/api/taskList"
  },
  {
    "metadata": "expense",
    "development": "http://localhost:3000/api/expense",
    "production": "http://34.70.243.4/personal/public/api/expense"
  },

  {
    "metadata": "report",
    "development": "http://localhost:3000/api/report",
    "production": "http://34.70.243.4/personal/public/api/report"
  },
  {
    "metadata": "event",
    "development": "http://localhost:3000/api/event",
    "production": "http://34.70.243.4/personal/public/api/event"
  },
  {
    "metadata": "google",
    "development": "http://localhost:3000/api/google",
    "production": "http://34.70.243.4/personal/public/api/google"
  }
]
